authtuna/__init__.py
authtuna/core/__init__.py
authtuna/core/config.py
authtuna/core/database.py
authtuna/core/defaults.py
authtuna/core/encryption.py
authtuna/core/exceptions.py
authtuna/core/mfa.py
authtuna/core/social.py
authtuna/core/passkeys/__init__.py
authtuna/helpers/__init__.py
authtuna/helpers/mail.py
authtuna/helpers/theme.py
authtuna/integrations/__init__.py
authtuna/integrations/fastapi_integration.py
authtuna/manager/__init__.py
authtuna/manager/asynchronous.py
authtuna/middlewares/__init__.py
authtuna/middlewares/session.py
authtuna/routers/__init__.py
authtuna/routers/admin.py
authtuna/routers/auth.py
authtuna/routers/mfa.py
authtuna/routers/passkey.py
authtuna/routers/passwordless.py
authtuna/routers/social.py
authtuna/routers/ui.py
authtuna/templates/dashboard/invite_accepted.html
authtuna/templates/dashboard/org_details.html
authtuna/templates/dashboard/organizations.html
authtuna/templates/dashboard/settings.html
authtuna/templates/dashboard/team_details.html
authtuna/templates/dashboard/user_dashboard.html
authtuna/templates/dashboard/user_profile.html
authtuna/templates/email/authorize_confirm.html
authtuna/templates/email/mfa_added.html
authtuna/templates/email/mfa_failed.html
authtuna/templates/email/mfa_removed.html
authtuna/templates/email/new_login.html
authtuna/templates/email/new_social_account_connected.html
authtuna/templates/email/org_invite.html
authtuna/templates/email/password_change.html
authtuna/templates/email/password_reset.html
authtuna/templates/email/passwordless_login.html
authtuna/templates/email/team_invite.html
authtuna/templates/email/verification.html
authtuna/templates/email/welcome.html
authtuna/templates/pages/admin_dashboard.html
authtuna/templates/pages/admin_role_detail.html
authtuna/templates/pages/admin_user_detail.html
authtuna/templates/pages/authorize_action.html
authtuna/templates/pages/error.html
authtuna/templates/pages/forgot_password.html
authtuna/templates/pages/login.html
authtuna-0.2.2.dist-info/licenses/LICENSE.txt
authtuna-0.2.2.dist-info/METADATA
authtuna-0.2.2.dist-info/WHEEL
authtuna-0.2.2.dist-info/top_level.txt
authtuna-0.2.2.dist-info/RECORD
