Metadata-Version: 2.4
Name: authtuna
Version: 0.2.2
Summary: A high-performance, framework-agnostic authorization and session management library for Python
Author-email: shashstormer <shashanka5398@gmail.com>
License: Copyright (c) 2024 shashstormer
Project-URL: Homepage, https://github.com/shashstormer/authtuna
Project-URL: Repository, https://github.com/shashstormer/authtuna
Project-URL: Documentation, https://authtuna.shashstorm.in/
Project-URL: Issues, https://github.com/shashstormer/authtuna/issues
Keywords: authentication,authorization,session,fastapi,security
Classifier: Development Status :: 4 - Beta
Classifier: Intended Audience :: Developers
Classifier: License :: OSI Approved :: MIT License
Classifier: Operating System :: OS Independent
Classifier: Programming Language :: Python :: 3 :: Only
Classifier: Programming Language :: Python :: 3.9
Classifier: Programming Language :: Python :: 3.10
Classifier: Programming Language :: Python :: 3.11
Classifier: Programming Language :: Python :: 3.12
Classifier: Programming Language :: Python :: 3.13
Classifier: Programming Language :: Python :: 3.14
Classifier: Topic :: Security
Classifier: Topic :: Software Development :: Libraries :: Python Modules
Requires-Python: >=3.9
License-File: LICENSE.txt
Requires-Dist: pydantic-settings>=2.0.0
Requires-Dist: sqlalchemy>=2.0.0
Requires-Dist: cryptography>=41.0.0
Requires-Dist: pyotp>=2.8.0
Requires-Dist: PyJWT>=2.8.0
Requires-Dist: python-jose[cryptography]>=3.3.0
Requires-Dist: aiosmtplib>=2.0.0
Requires-Dist: dkimpy>=1.1.0
Requires-Dist: slowapi>=0.1.0
Requires-Dist: authlib>=1.0.0
Requires-Dist: ua-parser>=0.10.0
Requires-Dist: bcrypt>=4.0.0
Requires-Dist: python-dotenv>=1.0.0
Requires-Dist: qrcode>=7.4.2
Requires-Dist: aiosqlite>=0.20.0
Requires-Dist: fastapi>=0.100.0
Requires-Dist: starlette>=0.27.0
Requires-Dist: Jinja2>=3.0.0
Requires-Dist: httpx
Requires-Dist: itsdangerous
Requires-Dist: uvicorn
Requires-Dist: cbor2>=5.4.6
Requires-Dist: python-multipart
Provides-Extra: passkey
Requires-Dist: pillow; extra == "passkey"
Provides-Extra: dev
Requires-Dist: pytest>=7.0.0; extra == "dev"
Requires-Dist: pytest-asyncio>=0.21.0; extra == "dev"
Requires-Dist: black>=23.0.0; extra == "dev"
Requires-Dist: isort>=5.12.0; extra == "dev"
Requires-Dist: flake8>=6.0.0; extra == "dev"
Requires-Dist: mypy>=1.0.0; extra == "dev"
Requires-Dist: httpx>=0.28.1; extra == "dev"
Requires-Dist: pytest-cov; extra == "dev"
Requires-Dist: pillow; extra == "dev"
Dynamic: license-file
